{
	"partitions" : [
		{
			"name" : "Top",
			"pins" : [
				{
					"name" : "audio_input.ready",
					"strict" : false
				},
				{
					"name" : "pitch_output.data[0]",
					"strict" : false
				},
				{
					"name" : "pitch_output.data[1]",
					"strict" : false
				},
				{
					"name" : "pitch_output.data[2]",
					"strict" : false
				},
				{
					"name" : "pitch_output.data[3]",
					"strict" : false
				},
				{
					"name" : "pitch_output.data[4]",
					"strict" : false
				},
				{
					"name" : "pitch_output.data[5]",
					"strict" : false
				},
				{
					"name" : "pitch_output.data[6]",
					"strict" : false
				},
				{
					"name" : "pitch_output.data[7]",
					"strict" : false
				},
				{
					"name" : "pitch_output.data[8]",
					"strict" : false
				},
				{
					"name" : "pitch_output.valid",
					"strict" : false
				},
				{
					"name" : "audio_clk",
					"strict" : false
				},
				{
					"name" : "reset",
					"strict" : false
				},
				{
					"name" : "audio_input.valid",
					"strict" : false
				},
				{
					"name" : "clk",
					"strict" : false
				},
				{
					"name" : "audio_input.data[10]",
					"strict" : false
				},
				{
					"name" : "audio_input.data[9]",
					"strict" : false
				},
				{
					"name" : "audio_input.data[8]",
					"strict" : false
				},
				{
					"name" : "audio_input.data[7]",
					"strict" : false
				},
				{
					"name" : "audio_input.data[6]",
					"strict" : false
				},
				{
					"name" : "audio_input.data[5]",
					"strict" : false
				},
				{
					"name" : "audio_input.data[4]",
					"strict" : false
				},
				{
					"name" : "audio_input.data[3]",
					"strict" : false
				},
				{
					"name" : "audio_input.data[2]",
					"strict" : false
				},
				{
					"name" : "audio_input.data[1]",
					"strict" : false
				},
				{
					"name" : "audio_input.data[0]",
					"strict" : false
				},
				{
					"name" : "audio_input.data[11]",
					"strict" : false
				},
				{
					"name" : "audio_input.data[12]",
					"strict" : false
				},
				{
					"name" : "audio_input.data[13]",
					"strict" : false
				},
				{
					"name" : "audio_input.data[14]",
					"strict" : false
				},
				{
					"name" : "audio_input.data[15]",
					"strict" : false
				}
			]
		}
	]
}